LICENSE
README.md
setup.cfg
setup.py
ezpacket/__init__.py
ezpacket/dynamic_section.py
ezpacket/errors.py
ezpacket/expanding_section.py
ezpacket/packet.py
ezpacket/section.py
ezpacket/zeros.py
ezpacket.egg-info/PKG-INFO
ezpacket.egg-info/SOURCES.txt
ezpacket.egg-info/dependency_links.txt
ezpacket.egg-info/top_level.txt