Metadata-Version: 2.1
Name: ezpacket
Version: 0.0.6
Summary: A module for writing easy to understand byte packets and byte manipulations
Home-page: https://github.com/ynsgnr/ez-packet
Author: Yunus Gungor
Author-email: yunusgnr@gmail.com
Classifier: Programming Language :: Python :: 3
Classifier: License :: OSI Approved :: MIT License
Classifier: Operating System :: OS Independent
License-File: LICENSE
